testpypissszczygielski/__init__.py
testpypissszczygielski/m_mod_sszczygielski.py
testpypisszczygielski-0.0.1.dist-info/LICENCE.txt
testpypisszczygielski-0.0.1.dist-info/METADATA
testpypisszczygielski-0.0.1.dist-info/WHEEL
testpypisszczygielski-0.0.1.dist-info/top_level.txt
testpypisszczygielski-0.0.1.dist-info/RECORD
