Metadata-Version: 2.1
Name: testpypisszczygielski
Version: 0.0.1
Summary: My test package
Author-email: Seba <sebastianszczy@gmail.com>
Keywords: testpypisszczygielski,name,sufname,fun
Classifier: Framework :: Django
Classifier: Programming Language :: Python :: 3
Requires-Python: >=3.7
License-File: LICENCE.txt
Requires-Dist: requests
Requires-Dist: importlib-metadata ; python_version < "3.8"
